{"uuids": {"phone_id": "483d6b0e-8727-4f99-8515-75090b24e85e", "uuid": "f2cf78cf-c862-489e-8165-7559f2ab7dc0", "client_session_id": "cc45f308-e9f5-481c-addd-68ced33325fb", "advertising_id": "0f153197-4951-4921-9861-252d10c76fce", "device_id": "android-ad9f5fbb58376bfb"}, "cookie": {"csrftoken": "YyLjDi4OyYeuzoneZPYDSr4pnJQgAeSt", "ds_user_id": "50137885539", "ig_direct_region_hint": "\"ASH\\05450137885539\\0541669408346:01f7a5038c756c68b895f3552d0872faa3fc1e9bc94c832351a2512200b5732c5810d401\"", "mid": "YZ_yzwABAAEqZ4T9nIzKXNS99S48", "rur": "\"NCG\\05450137885539\\0541669408349:01f738e67dc9b49b75044060e67f7b16a38ed79fde0355a2fa037d2f645f15c6884bd53a\"", "sessionid": "50137885539%3AWgVTOYycHtUQ5w%3A1"}, "timing_value": {"last_login": 1637872337.2892685, "last_experiments": 1637872337.2892685}, "device_settings": {"app_version": "117.0.0.28.123", "android_version": "28", "android_release": "9.0", "dpi": "420dpi", "resolution": "1080x1920", "manufacturer": "OnePlus", "device": "ONEPLUS A3003", "model": "OnePlus3", "cpu": "qcom", "version_code": "180322800"}, "user_agent": "Instagram 117.0.0.28.123 Android (28/9.0; 420dpi; 1080x1920; OnePlus; ONEPLUS A3003; OnePlus3; qcom; en_US; 180322800)"}